{
    "global": {
        "target_point": 5,
        "storage_bullet": 100,
        "cost": 0,
        "cost_recover_speed": 1,
        "instrument_ceiling": 5,
        "target_line": [[0.0, 720.0], [1280.0, 720.0]],
        "operation_background": "Resources/assets/images/map_tutorial_operation_background.png",
        "operation_background_expand": "Resources/assets/images/map_tutorial_operation_background_expand.png",
        "operation_start_background": "Resources/assets/images/map_tutorial_operation_start_background.png",
        "operation_over_background": "Resources/assets/images/map_tutorial_operation_start_background.png"
    },
    "target_enemy": [
        {
            "enemy_recognition_name": "Train_Target",
            "enemy_position": [640.0, 0.0],
            "enemy_size": [100.0, 100.0],
            "enemy_path": [
                "down"
            ],
            "enemy_approach_time": 13.0,
            "enemy_approach_alpha": 0,
            "enemy_increase_alpha_speed": 5
        },
        {
            "enemy_recognition_name": "Train_Target",
            "enemy_position": [640.0, 0.0],
            "enemy_size": [100.0, 100.0],
            "enemy_path": [
                "down"
            ],
            "enemy_approach_time": 16.0,
            "enemy_approach_alpha": 0,
            "enemy_increase_alpha_speed": 5
        },
        {
            "enemy_recognition_name": "Train_Target",
            "enemy_position": [640.0, 0.0],
            "enemy_size": [100.0, 100.0],
            "enemy_path": [
                "down"
            ],
            "enemy_approach_time": 19.0,
            "enemy_approach_alpha": 0,
            "enemy_increase_alpha_speed": 5
        },
        {
            "enemy_recognition_name": "Train_Target",
            "enemy_position": [640.0, 0.0],
            "enemy_size": [100.0, 100.0],
            "enemy_path": [
                "down"
            ],
            "enemy_approach_time": 22.0,
            "enemy_approach_alpha": 0,
            "enemy_increase_alpha_speed": 5
        }
    ],
    "message_box": [
        {
            "box_size": [300.0, 100.0],
            "box_image_path": "Resources/assets/images/tutorial_move.png",
            "box_title": [
                "移动枪口",
                "Move Muzzle"
            ],
            "box_content": [
                "移动鼠标以改变枪口位置。",
                "Move mouse to change muzzle position."
            ],
            "box_title_color": [255, 255, 255, 255],
            "box_content_color": [255, 255, 255, 255],
            "box_existing_time": 3.0,
            "box_appear_time": 1.0
        },
        {
            "box_size": [300.0, 100.0],
            "box_image_path": "Resources/assets/images/tutorial_fire.png",
            "box_title": [
                "开火",
                "Fire"
            ],
            "box_content": [
                "点击鼠标左键以发射子弹。",
                "Click LMB to fire."
            ],
            "box_title_color": [255, 255, 255, 255],
            "box_content_color": [255, 255, 255, 255],
            "box_existing_time": 3.0,
            "box_appear_time": 5.0
        },
        {
            "box_size": [300.0, 100.0],
            "box_image_path": "Resources/assets/images/tutorial_reload.png",
            "box_title": [
                "换弹",
                "Reload"
            ],
            "box_content": [
                "如果枪支子弹耗尽，向前推滚轮即可补充子弹。",
                "If the gun's bullets are exhausted, push the wheel forward to reload."
            ],
            "box_title_color": [255, 255, 255, 255],
            "box_content_color": [255, 255, 255, 255],
            "box_existing_time": 3.0,
            "box_appear_time": 9.0
        },
        {
            "box_size": [300.0, 100.0],
            "box_image_path": "Resources/assets/images/tutorial_defend.png",
            "box_title": [
                "守住阵地",
                "Defend"
            ],
            "box_content": [
                "不要让敌人到达你的目标区域（红线处）！",
                "Don't let enemy reach your target area (red line)!"
            ],
            "box_title_color": [255, 100, 100, 255],
            "box_content_color": [255, 255, 255, 255],
            "box_existing_time": 5.0,
            "box_appear_time": 13.0
        }
    ]
}